unisound_agent_frame/.gitignore
unisound_agent_frame/LICENSE
unisound_agent_frame/README.md
unisound_agent_frame/__init__.py
unisound_agent_frame/cli.py
unisound_agent_frame/service.py
unisound_agent_frame/agent/__init__.py
unisound_agent_frame/agent/agent.py
unisound_agent_frame/agent/agent_registry.py
unisound_agent_frame/base/__init__.py
unisound_agent_frame/base/component_manager.py
unisound_agent_frame/base/config_manager.py
unisound_agent_frame/base/framework.py
unisound_agent_frame/base/router_manager.py
unisound_agent_frame/concurrency/__init__.py
unisound_agent_frame/concurrency/agent_concurrency.py
unisound_agent_frame/concurrency/distributed_concurrency.py
unisound_agent_frame/demo/__init__.py
unisound_agent_frame/demo/agent/DemoAgent.py
unisound_agent_frame/demo/agent/__init__.py
unisound_agent_frame/domain/__init__.py
unisound_agent_frame/domain/models.py
unisound_agent_frame/domain/request_model.py
unisound_agent_frame/domain/response_model.py
unisound_agent_frame/exception/__init__.py
unisound_agent_frame/exception/business_exception.py
unisound_agent_frame/exception/exception_handler.py
unisound_agent_frame/llm/__init__.py
unisound_agent_frame/llm/gpt4_llm_connection.py
unisound_agent_frame/llm/llm_connection.py
unisound_agent_frame/llm/llm_connection_factory.py
unisound_agent_frame/llm/llm_pool.py
unisound_agent_frame/llm/unigpt_llm_connection.py
unisound_agent_frame/scripts/Dockerfile
unisound_agent_frame/scripts/__init__.py
unisound_agent_frame/scripts/shutdown.bat
unisound_agent_frame/scripts/shutdown.command
unisound_agent_frame/scripts/shutdown.sh
unisound_agent_frame/scripts/startup.bat
unisound_agent_frame/scripts/startup.command
unisound_agent_frame/scripts/startup.sh
unisound_agent_frame/scripts/supervisord.conf
unisound_agent_frame/template/__init__.py
unisound_agent_frame/template/demo_agent.template
unisound_agent_frame/template/frame_dev.template
unisound_agent_frame/template/settings.template
unisound_agent_frame/util/__init__.py
unisound_agent_frame-0.0.3.dist-info/licenses/unisound_agent_frame/LICENSE
unisound_agent_frame-0.0.3.dist-info/METADATA
unisound_agent_frame-0.0.3.dist-info/WHEEL
unisound_agent_frame-0.0.3.dist-info/entry_points.txt
unisound_agent_frame-0.0.3.dist-info/top_level.txt
unisound_agent_frame-0.0.3.dist-info/RECORD
