Metadata-Version: 2.4
Name: unisound-agent-frame
Version: 0.0.3
Summary: # Unisound Agent Framework
Home-page: https://github.com/yourusername/my-framework
Author: unisound
Author-email: your.email@example.com
License: MIT
Classifier: Programming Language :: Python :: 3
Classifier: Operating System :: OS Independent
Requires-Python: >=3.5
License-File: unisound_agent_frame/LICENSE
Requires-Dist: fastapi>=0.68.0
Requires-Dist: uvicorn>=0.15.0
Requires-Dist: sqlalchemy>=1.4.0
Requires-Dist: aiofiles>=0.8.0
Requires-Dist: aioredis>=2.0.0
Requires-Dist: pyyaml>=6.0
Requires-Dist: python-multipart>=0.0.5
Requires-Dist: aiomysql>=0.1.1
Requires-Dist: aiohttp>=3.8.0
Requires-Dist: loguru>=0.6.0
Requires-Dist: starlette>=0.21.0
Dynamic: author
Dynamic: author-email
Dynamic: classifier
Dynamic: description
Dynamic: description-content-type
Dynamic: home-page
Dynamic: license
Dynamic: license-file
Dynamic: requires-dist
Dynamic: requires-python
Dynamic: summary
